dispatcher_plugin_integral_all_sky/SpicasApiDispatcher.ipynb
dispatcher_plugin_integral_all_sky/__init__.py
dispatcher_plugin_integral_all_sky/exposer.py
dispatcher_plugin_integral_all_sky/spiacs.py
dispatcher_plugin_integral_all_sky/spiacs_dataserver_dispatcher.py
dispatcher_plugin_integral_all_sky/spiacs_lightcurve_query.py
dispatcher_plugin_integral_all_sky/config_dir/data_server_conf.yml
dispatcher_plugin_integral_all_sky-1.0.dist-info/LICENSE.rst
dispatcher_plugin_integral_all_sky-1.0.dist-info/METADATA
dispatcher_plugin_integral_all_sky-1.0.dist-info/WHEEL
dispatcher_plugin_integral_all_sky-1.0.dist-info/top_level.txt
dispatcher_plugin_integral_all_sky-1.0.dist-info/RECORD
