Metadata-Version: 2.1
Name: dispatcher-plugin-integral-all-sky
Version: 1.0
Summary: A plugin for online data analysis
Home-page: UNKNOWN
Author: Andrea Tramacere
Author-email: andrea.tramacere@unige.ch
License: UNKNOWN
Platform: UNKNOWN
Requires-Dist: astropy
Requires-Dist: simple-logger
Requires-Dist: numpy
Provides-Extra: test
Requires-Dist: pytest ; extra == 'test'
Requires-Dist: pytest-depends ; extra == 'test'
